LICENSE
README.md
setup.cfg
setup.py
vxwk/__init__.py
vxwk/__version__.py
vxwk/carddy.py
vxwk/cardwx.py
vxwk/client.py
vxwk/controller.py
vxwk/external.py
vxwk/livecode.py
vxwk/livecodefile.py
vxwk/options.py
vxwk/shortlink.py
vxwk/uhmac.py
vxwk/ujson.py
vxwk/ulist.py
vxwk/uquery.py
vxwk/urandom.py
wuntsong_vxwk.egg-info/PKG-INFO
wuntsong_vxwk.egg-info/SOURCES.txt
wuntsong_vxwk.egg-info/dependency_links.txt
wuntsong_vxwk.egg-info/requires.txt
wuntsong_vxwk.egg-info/top_level.txt