Metadata-Version: 2.1
Name: wuntsong-vxwk
Version: 1.0.4
Summary: VXWK项目的Python版本SDK
Home-page: https://www.vxwk.com
Author: 广州桓创信息科技有限公司
Author-email: report@wuntsong.com
License-File: LICENSE
Requires-Dist: certifi==2023.11.17
Requires-Dist: charset-normalizer==3.3.2
Requires-Dist: idna==3.6
Requires-Dist: requests==2.31.0
Requires-Dist: urllib3==2.1.0
